oresat_dxwifi/__init__.py
oresat_dxwifi/__main__.py
oresat_dxwifi/_version.py
oresat_dxwifi/camera/CMakeLists.txt
oresat_dxwifi/camera/README.md
oresat_dxwifi/camera/frame.py
oresat_dxwifi/camera/interface.py
oresat_dxwifi/resources/__init__.py
oresat_dxwifi/resources/temperature.py
oresat_dxwifi/services/oresat_live.py
oresat_dxwifi/services/configs/camera_configs.yaml
oresat_dxwifi/services/static/SMPTE_Color_Bars.gif
oresat_dxwifi/templates/oresat_live.html
oresat_dxwifi/transmission/__init__.py
oresat_dxwifi/transmission/defaults.py
oresat_dxwifi/transmission/startmonitor.sh
oresat_dxwifi/transmission/transmission.py
oresat_dxwifi/transmission/tx_module.so
oresat_dxwifi/transmission/configs/transmission_configs.yaml
oresat_dxwifi-0.3.8.dist-info/LICENSE
oresat_dxwifi-0.3.8.dist-info/METADATA
oresat_dxwifi-0.3.8.dist-info/WHEEL
oresat_dxwifi-0.3.8.dist-info/entry_points.txt
oresat_dxwifi-0.3.8.dist-info/top_level.txt
oresat_dxwifi-0.3.8.dist-info/RECORD
