Metadata-Version: 2.1
Name: oresat-dxwifi
Version: 0.3.8
Summary: OreSat DxWiFi OLAF app
License: GPL-3.0
Classifier: License :: OSI Approved :: GNU General Public License v3 (GPLv3)
Classifier: Operating System :: POSIX :: Linux
Classifier: Programming Language :: Python :: 3
Classifier: Programming Language :: Python :: 3.7
Classifier: Programming Language :: Python :: 3.8
Classifier: Programming Language :: Python :: 3.9
Classifier: Programming Language :: Python :: 3.10
Classifier: Programming Language :: Python :: 3.11
Classifier: Topic :: Software Development :: Embedded Systems
Requires-Python: >=3.7
License-File: LICENSE
Requires-Dist: oresat-configs
Requires-Dist: oresat-olaf >=3.0.0
Requires-Dist: v4l2py ==2.1.0
